polymatheia_tools/__init__.py
polymatheia_tools/analysis.py
polymatheia_tools/config.py
polymatheia_tools/download/__init__.py
polymatheia_tools/download/catalogue.py
polymatheia_tools/download/common.py
polymatheia_tools/download/config.py
polymatheia_tools/download/exceptions.py
polymatheia_tools/download/main.py
polymatheia_tools/download/query.py
polymatheia_tools/download/sru_call.py
polymatheia_tools/extraction.py
polymatheia_tools/parsing.py
polymatheia_tools/utils.py
polymatheia_tools/visualization.py
polymatheia_tools-0.1.1.dist-info/WHEEL
polymatheia_tools-0.1.1.dist-info/METADATA
polymatheia_tools-0.1.1.dist-info/RECORD
